memory_compressed_attention/__init__.py
memory_compressed_attention/memory_compressed_attention.py
memory_compressed_attention-0.0.7.dist-info/LICENSE
memory_compressed_attention-0.0.7.dist-info/METADATA
memory_compressed_attention-0.0.7.dist-info/WHEEL
memory_compressed_attention-0.0.7.dist-info/top_level.txt
memory_compressed_attention-0.0.7.dist-info/RECORD
