Metadata-Version: 2.1
Name: memory-compressed-attention
Version: 0.0.7
Summary: Memory-Compressed Self Attention
Home-page: https://github.com/lucidrains/memory-compressed-attention
Author: Phil Wang
Author-email: lucidrains@gmail.com
License: MIT
Keywords: transformers,artificial intelligence,attention mechanism
Classifier: Development Status :: 4 - Beta
Classifier: Intended Audience :: Developers
Classifier: Topic :: Scientific/Engineering :: Artificial Intelligence
Classifier: License :: OSI Approved :: MIT License
Classifier: Programming Language :: Python :: 3.6
License-File: LICENSE
Requires-Dist: torch
